lpsolvers/__init__.py
lpsolvers/cdd_.py
lpsolvers/cvxopt_.py
lpsolvers/cvxpy_.py
lpsolvers/exceptions.py
lpsolvers/pdlp_.py
lpsolvers/proxqp_.py
lpsolvers-2.1.0.dist-info/LICENSE
lpsolvers-2.1.0.dist-info/WHEEL
lpsolvers-2.1.0.dist-info/METADATA
lpsolvers-2.1.0.dist-info/RECORD
